MANIFEST.in
README.rst
setup.py
src/cextrema.c
src/cvort.c
stormtracks/__init__.py
stormtracks/c20data.py
stormtracks/download.py
stormtracks/ibtracsdata.py
stormtracks/load_settings.py
stormtracks/results.py
stormtracks/setup_logging.py
stormtracks/stormtracks-admin.py
stormtracks/version.py
stormtracks.egg-info/PKG-INFO
stormtracks.egg-info/SOURCES.txt
stormtracks.egg-info/dependency_links.txt
stormtracks.egg-info/requires.txt
stormtracks.egg-info/top_level.txt
stormtracks/analysis/__init__.py
stormtracks/analysis/cal_val_analysis.py
stormtracks/analysis/figure_plotting.py
stormtracks/analysis/plotting.py
stormtracks/installation/__init__.py
stormtracks/installation/classifiers/classifier_cc_0p5_0p79.json
stormtracks/installation/classifiers/classifier_cc_best.json
stormtracks/installation/classifiers/classifier_chain_qdc_cc_0p66_op66.json
stormtracks/installation/classifiers/classifier_chain_qdc_cc_best.json
stormtracks/installation/classifiers/classifier_ldc_best.json
stormtracks/installation/classifiers/classifier_qdc1.json
stormtracks/installation/classifiers/classifier_qdc_0p75_0p60.json
stormtracks/installation/classifiers/classifier_qdc_0p82_0p47.json
stormtracks/installation/classifiers/classifier_qdc_0p84_0p40.json
stormtracks/installation/classifiers/classifier_qdc_best.json
stormtracks/installation/classifiers/classifier_sgdc_0p63_0p75.json
stormtracks/installation/classifiers/classifier_sgdc_best.json
stormtracks/installation/plots/plot_match_comp_1.json
stormtracks/installation/plots/plot_match_comp_2.json
stormtracks/installation/plots/plot_matches_start.json
stormtracks/installation/plots/plot_plot3.json
stormtracks/installation/plots/plot_press_vort.json
stormtracks/installation/plots/plot_settings1.json
stormtracks/installation/plots/plot_temp.json
stormtracks/installation/plots/plot_temp2.json
stormtracks/installation/requirements/conda_pip_requirements.txt
stormtracks/installation/requirements/conda_requirements.txt
stormtracks/installation/requirements/requirements_a.txt
stormtracks/installation/requirements/requirements_analysis.txt
stormtracks/installation/requirements/requirements_b.txt
