Metadata-Version: 1.1
Name: stormtracks
Version: 0.5.2.4
Summary: Tropical Cyclone Detection and Tracking
Home-page: https://github.com/markmuetz/stormtracks
Author: Mark Muetzelfeldt
Author-email: markmuetz@gmail.com
License: UNKNOWN
Keywords: tropical cyclone track detection
Platform: UNKNOWN
Classifier: Development Status :: 3 - Alpha
Classifier: Environment :: Console
Classifier: Intended Audience :: Science/Research
Classifier: License :: OSI Approved :: MIT License
Classifier: Natural Language :: English
Classifier: Operating System :: POSIX :: Linux
Classifier: Programming Language :: Python :: 2.7
Classifier: Programming Language :: C
Classifier: Topic :: Scientific/Engineering :: Atmospheric Science
